sim_lab/__init__.py
sim_lab/cli/__init__.py
sim_lab/cli/main.py
sim_lab/config/__init__.py
sim_lab/config/settings.py
sim_lab/core/__init__.py
sim_lab/core/agent_based_simulation.py
sim_lab/core/base_simulation.py
sim_lab/core/cellular_automaton_simulation.py
sim_lab/core/discrete_event_simulation.py
sim_lab/core/epidemiological_simulation.py
sim_lab/core/markov_chain_simulation.py
sim_lab/core/monte_carlo_simulation.py
sim_lab/core/network_simulation.py
sim_lab/core/predator_prey_simulation.py
sim_lab/core/product_popularity_simulation.py
sim_lab/core/queueing_simulation.py
sim_lab/core/registry.py
sim_lab/core/resource_fluctuations_simulation.py
sim_lab/core/stock_market_simulation.py
sim_lab/core/supply_chain_simulation.py
sim_lab/core/system_dynamics_simulation.py
sim_lab/tui/__init__.py
sim_lab/tui/app.py
sim_lab/utils/__init__.py
sim_lab/utils/io.py
sim_lab/utils/validation.py
sim_lab/viz/__init__.py
sim_lab/viz/plots.py
sim_lab/web/__init__.py
sim_lab/web/app.py
sim_lab-0.4.1.dist-info/licenses/LICENSE
sim_lab-0.4.1.dist-info/METADATA
sim_lab-0.4.1.dist-info/WHEEL
sim_lab-0.4.1.dist-info/entry_points.txt
sim_lab-0.4.1.dist-info/top_level.txt
sim_lab-0.4.1.dist-info/RECORD
