Metadata-Version: 2.4
Name: sim-lab
Version: 0.4.1
Summary: A set of classes for simulating various business-related scenarios for educational use
Author-email: Michael Borck <michael@borck.me>
License-Expression: MIT
Project-URL: Homepage, http://sim-lab.borck.me
Project-URL: Documentation, https://michael-borck.github.io/sim-lab/
Project-URL: Repository, https://github.com/michael-borck/sim-lab
Classifier: Development Status :: 4 - Beta
Classifier: Programming Language :: Python :: 3
Classifier: Programming Language :: Python :: 3.10
Classifier: Programming Language :: Python :: 3.11
Classifier: Programming Language :: Python :: 3.12
Classifier: Intended Audience :: Education
Classifier: Topic :: Scientific/Engineering :: Information Analysis
Requires-Python: >=3.10
License-File: LICENSE
Requires-Dist: numpy>=1.26.0
Requires-Dist: typer[all]>=0.9.0
Requires-Dist: uvicorn>=0.29.0
Requires-Dist: textual>=0.52.1
Requires-Dist: matplotlib>=3.8.0
Requires-Dist: plotly>=5.19.0
Requires-Dist: pydantic>=2.7.0
Requires-Dist: pymdown-extensions>=10.8.1
Requires-Dist: pycparser>=2.22
Requires-Dist: jinja2>=3.1.3
Requires-Dist: python-fasthtml>=0.1.0
Provides-Extra: dev
Requires-Dist: pytest>=8.2.0; extra == "dev"
Requires-Dist: pytest-cov>=4.1.0; extra == "dev"
Requires-Dist: mkdocs>=1.6.0; extra == "dev"
Requires-Dist: mkdocs-material>=9.5.2; extra == "dev"
Requires-Dist: mkdocstrings>=0.25.0; extra == "dev"
Requires-Dist: mkdocstrings-python>=1.10.0; extra == "dev"
Requires-Dist: ruff>=0.1.5; extra == "dev"
Requires-Dist: mypy>=1.8.0; extra == "dev"
Requires-Dist: build>=1.0.0; extra == "dev"
Requires-Dist: twine==6.0.1; extra == "dev"
Provides-Extra: web
Requires-Dist: uvicorn>=0.29.0; extra == "web"
Requires-Dist: python-fasthtml>=0.1.0; extra == "web"
Provides-Extra: cli
Requires-Dist: typer[all]>=0.9.0; extra == "cli"
Dynamic: license-file
